cryptopyx-0.1.1.dist-info/METADATA
cryptopyx-0.1.1.dist-info/WHEEL
cryptopyx-0.1.1.dist-info/licenses/LICENSE
cryptopyx/__init__.py
cryptopyx/_cryptopyx.abi3.so
cryptopyx-0.1.1.dist-info/RECORD
