Metadata-Version: 2.4
Name: cryptopyx
Version: 0.1.1
Classifier: Topic :: Security :: Cryptography
Classifier: Topic :: Software Development :: Libraries :: Python Modules
Classifier: Topic :: Scientific/Engineering
Classifier: Natural Language :: English
Classifier: Intended Audience :: Developers
Classifier: Intended Audience :: Education
Classifier: Intended Audience :: Science/Research
Classifier: Development Status :: 5 - Production/Stable
Classifier: Programming Language :: Python :: 3 :: Only
Classifier: Programming Language :: Python :: 3.9
Classifier: Programming Language :: Python :: 3.10
Classifier: Programming Language :: Python :: 3.11
Classifier: Programming Language :: Python :: 3.12
Classifier: Programming Language :: Python :: 3.13
Classifier: Programming Language :: Rust
Classifier: Programming Language :: Python :: Implementation :: CPython
Classifier: Operating System :: OS Independent
Classifier: Typing :: Typed
License-File: LICENSE
Summary: A simple cryptography package written in Rust
Keywords: cryptography,cipher,encryption,decryption,security
Author-email: Siqi Yan <syan235711@gmail.com>
License-Expression: MIT
Requires-Python: >=3.9
Project-URL: Repository, https://github.com/syan212/CryptoPyX
Project-URL: issues, https://github.com/syan212/CryptoPyX/issues
Project-URL: Changelog, https://github.com/syan212/CryptoPyX/blob/main/CHANGELOG.md
